MANIFEST.in
setup.py
src/zc/__init__.py
src/zc.time.egg-info/PKG-INFO
src/zc.time.egg-info/SOURCES.txt
src/zc.time.egg-info/dependency_links.txt
src/zc.time.egg-info/namespace_packages.txt
src/zc.time.egg-info/not-zip-safe
src/zc.time.egg-info/requires.txt
src/zc.time.egg-info/top_level.txt
src/zc/time/README.txt
src/zc/time/__init__.py
src/zc/time/tests.py