Metadata-Version: 1.0
Name: zc.time
Version: 1.0.2
Summary: Hook time for testing
Home-page: UNKNOWN
Author: UNKNOWN
Author-email: UNKNOWN
License: ZPL 2.1
Platform: UNKNOWN
